dataset_load/.DS_Store
dataset_load/__init__.py
my_krml_25763727/.DS_Store
my_krml_25763727/__init__.py
my_krml_25763727/data/__init__.py
my_krml_25763727/data/sets.py
my_krml_25763727/features/dates.py
my_krml_25763727/models/null.py
my_krml_25763727/models/performance.py
dataset_load-2025.0.3.0.dist-info/METADATA
dataset_load-2025.0.3.0.dist-info/WHEEL
dataset_load-2025.0.3.0.dist-info/RECORD
